LICENCE
README.md
setup.py
rabbitmq_plus/__init__.py
rabbitmq_plus.egg-info/PKG-INFO
rabbitmq_plus.egg-info/SOURCES.txt
rabbitmq_plus.egg-info/dependency_links.txt
rabbitmq_plus.egg-info/requires.txt
rabbitmq_plus.egg-info/top_level.txt
rabbitmq_plus.egg-info/zip-safe
rabbitmq_plus/base/__init__.py
rabbitmq_plus/base/consumer.py
rabbitmq_plus/base/context.py
rabbitmq_plus/base/integrated.py
rabbitmq_plus/base/producer.py
rabbitmq_plus/base/properties.py
rabbitmq_plus/test/__init__.py
rabbitmq_plus/test/flask_integrated.py
rabbitmq_plus/test/func.py
rabbitmq_plus/test/standalone_run.py